g_checker_for_itf/ArgParser.py
g_checker_for_itf/Color.py
g_checker_for_itf/Dir.py
g_checker_for_itf/RecognizedFilter.py
g_checker_for_itf/__init__.py
g_checker_for_itf/main.py
g_checker_for_itf-0.0.dist-info/LICENSE
g_checker_for_itf-0.0.dist-info/METADATA
g_checker_for_itf-0.0.dist-info/WHEEL
g_checker_for_itf-0.0.dist-info/entry_points.txt
g_checker_for_itf-0.0.dist-info/top_level.txt
g_checker_for_itf-0.0.dist-info/RECORD
