Metadata-Version: 2.1
Name: g-checker-for-itf
Version: 0.0
Summary: "A checker if your credits meet the graduation requirements or not (For Univ. Tsukuba students)"
Author: oshamashama
Author-email: uwyiqmq@gmail.com
License: MIT
Platform: UNKNOWN
Classifier: Development Status :: 3 - Alpha
Classifier: Programming Language :: Python :: 3.7
Classifier: Programming Language :: Python :: 3.8
Classifier: Programming Language :: Python :: 3.9
Classifier: Programming Language :: Python :: 3.10
Requires-Python: >=3.7
License-File: LICENSE
Provides-Extra: dev
Requires-Dist: black (>=22.1.0) ; extra == 'dev'
Requires-Dist: flake8 (>=4.0.1) ; extra == 'dev'
Requires-Dist: mypy (>=0.931) ; extra == 'dev'
Requires-Dist: isort (>=5.10.1) ; extra == 'dev'
Requires-Dist: types-setuptools (>=57.4.8) ; extra == 'dev'
